odoo/addons/partner_code_program_territory/README.rst
odoo/addons/partner_code_program_territory/__init__.py
odoo/addons/partner_code_program_territory/__manifest__.py
odoo/addons/partner_code_program_territory/hooks.py
odoo/addons/partner_code_program_territory/i18n/es.po
odoo/addons/partner_code_program_territory/models/__init__.py
odoo/addons/partner_code_program_territory/models/res_partner.py
odoo/addons/partner_code_program_territory/models/res_partner_code_program.py
odoo/addons/partner_code_program_territory/models/res_partner_code_program_territory.py
odoo/addons/partner_code_program_territory/models/res_partner_code_program_territory_mixin.py
odoo/addons/partner_code_program_territory/readme/CONFIGURE.md
odoo/addons/partner_code_program_territory/readme/CONTRIBUTORS.md
odoo/addons/partner_code_program_territory/readme/DESCRIPTION.md
odoo/addons/partner_code_program_territory/readme/INSTALL.md
odoo/addons/partner_code_program_territory/readme/USAGE.md
odoo/addons/partner_code_program_territory/security/ir.model.access.csv
odoo/addons/partner_code_program_territory/static/description/icon.png
odoo/addons/partner_code_program_territory/static/description/index.html
odoo/addons/partner_code_program_territory/tests/__init__.py
odoo/addons/partner_code_program_territory/tests/test_partner_code_program_territory.py
odoo/addons/partner_code_program_territory/views/res_partner_code_program_territory_views.xml
odoo/addons/partner_code_program_territory/views/res_partner_code_program_views.xml
odoo/addons/partner_code_program_territory/views/res_partner_views.xml
odoo_addon_partner_code_program_territory-18.0.1.0.0.1.dist-info/METADATA
odoo_addon_partner_code_program_territory-18.0.1.0.0.1.dist-info/WHEEL
odoo_addon_partner_code_program_territory-18.0.1.0.0.1.dist-info/top_level.txt
odoo_addon_partner_code_program_territory-18.0.1.0.0.1.dist-info/RECORD
